bands_inspect/__init__.py
bands_inspect/_cli.py
bands_inspect/compare/__init__.py
bands_inspect/compare/align.py
bands_inspect/compare/difference.py
bands_inspect/eigenvals.py
bands_inspect/io/__init__.py
bands_inspect/io/_legacy/__init__.py
bands_inspect/io/_legacy/_hdf5_utils.py
bands_inspect/io/_save_load.py
bands_inspect/kpoints/__init__.py
bands_inspect/kpoints/_base.py
bands_inspect/kpoints/_explicit.py
bands_inspect/kpoints/_mesh.py
bands_inspect/kpoints/_path.py
bands_inspect/lattice.py
bands_inspect/plot.py
bands_inspect-0.3.2.dist-info/LICENSE.txt
bands_inspect-0.3.2.dist-info/METADATA
bands_inspect-0.3.2.dist-info/WHEEL
bands_inspect-0.3.2.dist-info/entry_points.txt
bands_inspect-0.3.2.dist-info/RECORD
